{
 "generated": "2026-07-05 19:30",
 "jobs": [
  {
   "id": "keiri-kickoff",
   "label": "経理キックオフ",
   "schedule": "毎月1日 9:00"
  },
  {
   "id": "monthly-reports",
   "label": "月次レポート一括",
   "schedule": "毎月3日 9:00"
  },
  {
   "id": "zehn-weekly",
   "label": "Zehn週次News下書き",
   "schedule": "月曜 10:00"
  },
  {
   "id": "roblox-weekly",
   "label": "Roblox事業 週次",
   "schedule": "月曜 11:00"
  },
  {
   "id": "studio-weekly",
   "label": "スタジオ運用レポート",
   "schedule": "月曜 12:00"
  },
  {
   "id": "ai-weekly",
   "label": "AI事業 週次",
   "schedule": "火曜 9:00"
  },
  {
   "id": "minutes-to-wiki",
   "label": "文字起こし→ナレッジ反映",
   "schedule": "毎日 18:00"
  }
 ],
 "links": [
  {
   "label": "IronPM（タスク管理）",
   "url": "https://iron-pm.onrender.com"
  },
  {
   "label": "スタジオ運用ダッシュボード",
   "url": "https://zehnstudio26.github.io/zehn-dashboard/"
  },
  {
   "label": "Handleループ（週次オーガニック）",
   "url": "https://docs.google.com/spreadsheets/d/1nwEVuPoILDxXRwHimsOFwMnhuNwWKhLn98lugJwh6UA/edit?gid=1704484867#gid=1704484867"
  }
 ],
 "runs": [
  {
   "start": "2026-07-04T13:20:33",
   "exit": 0,
   "minutes": 0.0,
   "job": "selftest"
  },
  {
   "start": "2026-07-04T22:35:38",
   "exit": 0,
   "minutes": 0.0,
   "job": "selftest"
  },
  {
   "start": "2026-07-04T22:37:59",
   "exit": 0,
   "minutes": 0.0,
   "job": "selftest"
  },
  {
   "start": "2026-07-05T16:23:30",
   "exit": 0,
   "minutes": 14.2,
   "job": "minutes-to-wiki"
  },
  {
   "start": "2026-07-05T17:30:02",
   "exit": 0,
   "minutes": 0.3,
   "job": "inbox-cycle"
  },
  {
   "start": "2026-07-05T17:40:02",
   "exit": 0,
   "minutes": 0.3,
   "job": "inbox-cycle"
  },
  {
   "start": "2026-07-05T17:50:02",
   "exit": 0,
   "minutes": 0.3,
   "job": "inbox-cycle"
  },
  {
   "start": "2026-07-05T18:00:00",
   "exit": 0,
   "minutes": 0.0,
   "job": "minutes-to-wiki"
  },
  {
   "start": "2026-07-05T18:00:01",
   "exit": 0,
   "minutes": 0.5,
   "job": "inbox-cycle"
  },
  {
   "start": "2026-07-05T18:10:02",
   "exit": 0,
   "minutes": 0.5,
   "job": "inbox-cycle"
  },
  {
   "start": "2026-07-05T18:20:02",
   "exit": 0,
   "minutes": 0.5,
   "job": "inbox-cycle"
  },
  {
   "start": "2026-07-05T18:30:02",
   "exit": 0,
   "minutes": 0.4,
   "job": "inbox-cycle"
  },
  {
   "start": "2026-07-05T18:40:02",
   "exit": 0,
   "minutes": 0.4,
   "job": "inbox-cycle"
  },
  {
   "start": "2026-07-05T18:50:02",
   "exit": 0,
   "minutes": 0.4,
   "job": "inbox-cycle"
  },
  {
   "start": "2026-07-05T19:00:02",
   "exit": 0,
   "minutes": 0.4,
   "job": "inbox-cycle"
  },
  {
   "start": "2026-07-05T19:10:02",
   "exit": 0,
   "minutes": 0.4,
   "job": "inbox-cycle"
  },
  {
   "start": "2026-07-05T19:20:02",
   "exit": 0,
   "minutes": 0.4,
   "job": "inbox-cycle"
  },
  {
   "start": "2026-07-05T19:30:02",
   "exit": 0,
   "minutes": 0.5,
   "job": "inbox-cycle"
  }
 ]
}